<?xml version="1.0" encoding="utf-8" ?>
<!--
=========================================================================================================
  Module      : モバイルドメイン設定XML(MobileDomainSetting.xml)
 ･･･････････････････････････････････････････････････････････････････････････････････････････････････････
  Copyright   : Copyright w2solution Co.,Ltd. 2009 All Rights Reserved.
=========================================================================================================
-->
<MobileDomainSetting>
  <Domain CareerId="01dc">@docomo.ne.jp</Domain>
  <Domain CareerId="02au">@ezweb.ne.jp</Domain>
  <Domain CareerId="03vd">@softbank.ne.jp</Domain>
  <Domain CareerId="03vd">.softbank.ne.jp</Domain>
  <Domain CareerId="03vd">.vodafone.ne.jp</Domain>
  <Domain CareerId="03vd">@disney.ne.jp</Domain>
  <Domain>@pdx.ne.jp</Domain>
  <Domain>.pdx.ne.jp</Domain>
</MobileDomainSetting>