<?xml version="1.0" encoding="utf-8" ?>
<!--
=========================================================================================================
  Module      : マスタ出力定義設定XML(MasterExportSetting.xml)
 ･･･････････････････････････････････････････････････････････････････････････････････････････････････････
  Copyright   : Copyright W2 Co.,Ltd. 2009 All Rights Reserved.
=========================================================================================================
-->
<MasterExportSetting>

  <AffiliateCoopLog>
    <Field jname="ログNo" name="log_no" field="w2_AffiliateCoopLog.log_no" />
    <Field jname="アフィリエイト区分" name="affiliate_kbn" field="w2_AffiliateCoopLog.affiliate_kbn" />
    <Field jname="マスタID" name="master_id" field="w2_AffiliateCoopLog.master_id" />
    <Field jname="連携ステータス" name="coop_status" field="w2_AffiliateCoopLog.coop_status" />
    <Field jname="連携データ1" name="coop_data1" field="w2_AffiliateCoopLog.coop_data1" />
    <Field jname="連携データ2" name="coop_data2" field="w2_AffiliateCoopLog.coop_data2" />
    <Field jname="連携データ3" name="coop_data3" field="w2_AffiliateCoopLog.coop_data3" />
    <Field jname="連携データ4" name="coop_data4" field="w2_AffiliateCoopLog.coop_data4" />
    <Field jname="連携データ5" name="coop_data5" field="w2_AffiliateCoopLog.coop_data5" />
    <Field jname="連携データ6" name="coop_data6" field="w2_AffiliateCoopLog.coop_data6" />
    <Field jname="連携データ7" name="coop_data7" field="w2_AffiliateCoopLog.coop_data7" />
    <Field jname="連携データ8" name="coop_data8" field="w2_AffiliateCoopLog.coop_data8" />
    <Field jname="連携データ9" name="coop_data9" field="w2_AffiliateCoopLog.coop_data9" />
    <Field jname="連携データ10" name="coop_data10" field="w2_AffiliateCoopLog.coop_data10" />
    <Field jname="連携データ11" name="coop_data11" field="w2_AffiliateCoopLog.coop_data11" />
    <Field jname="作成日" name="date_created" field="w2_AffiliateCoopLog.date_created" type="datetime" />
    <Field jname="更新日" name="date_changed" field="w2_AffiliateCoopLog.date_changed" type="datetime" />
    <Field jname="最終更新者" name="last_changed" field="w2_AffiliateCoopLog.last_changed" />
  </AffiliateCoopLog>
  <TargetListData>
    <Field jname="ユーザーID" name="user_id" field="w2_User.user_id" />
    <Field jname="顧客区分" name="user_kbn" field="w2_User.user_kbn" />
    <Field jname="外部連携モールID" name="mall_id" field="w2_User.mall_id" />
    <Field jname="氏名" name="name" field="w2_User.name" />
    <Field jname="氏名1" name="name1" field="w2_User.name1" />
    <Field jname="氏名2" name="name2" field="w2_User.name2" />
    <Field jname="氏名かな" name="name_kana" field="w2_User.name_kana" />
    <Field jname="氏名かな1" name="name_kana1" field="w2_User.name_kana1" />
    <Field jname="氏名かな2" name="name_kana2" field="w2_User.name_kana2" />
    <Field jname="ニックネーム" name="nick_name" field="w2_User.nick_name" />
    <Field jname="ＰＣメールアドレス" name="mail_addr" field="w2_User.mail_addr" />
    <Field jname="携帯メールアドレス" name="mail_addr2" field="w2_User.mail_addr2" />
    <Field jname="郵便番号" name="zip" field="w2_User.zip" />
    <Field jname="郵便番号1" name="zip1" field="w2_User.zip1" />
    <Field jname="郵便番号2" name="zip2" field="w2_User.zip2" />
    <Field jname="住所" name="addr" field="w2_User.addr" />
    <Field jname="住所1" name="addr1" field="w2_User.addr1" />
    <Field jname="住所2" name="addr2" field="w2_User.addr2" />
    <Field jname="住所3" name="addr3" field="w2_User.addr3" />
    <Field jname="住所4" name="addr4" field="w2_User.addr4" />
    <Field jname="住所5" name="addr5" field="w2_User.addr5" />
    <Field jname="住所国名" name="addr_country_name" field="w2_User.addr_country_name" />
    <Field jname="電話番号1" name="tel1" field="w2_User.tel1" />
    <Field jname="電話番号1-1" name="tel1_1" field="w2_User.tel1_1" />
    <Field jname="電話番号1-2" name="tel1_2" field="w2_User.tel1_2" />
    <Field jname="電話番号1-3" name="tel1_3" field="w2_User.tel1_3" />
    <Field jname="電話番号（予備）2" name="tel2" field="w2_User.tel2" />
    <Field jname="電話番号（予備）2-1" name="tel2_1" field="w2_User.tel2_1" />
    <Field jname="電話番号（予備）2-2" name="tel2_2" field="w2_User.tel2_2" />
    <Field jname="電話番号（予備）2-3" name="tel2_3" field="w2_User.tel2_3" />
    <Field jname="性別" name="sex" field="w2_User.sex" />
    <Field jname="生年月日" name="birth" field="w2_User.birth" type="datetime" />
    <Field jname="生年月日（年）" name="birth_year" field="w2_User.birth_year" />
    <Field jname="生年月日（月）" name="birth_month" field="w2_User.birth_month" />
    <Field jname="生年月日（日）" name="birth_day" field="w2_User.birth_day" />
    <Field jname="企業名" name="company_name" field="w2_User.company_name" />
    <Field jname="部署名" name="company_post_name" field="w2_User.company_post_name" />
    <Field jname="ログインＩＤ" name="login_id" field="w2_User.login_id" />
    <Field jname="キャリアID" name="career_id" field="w2_User.career_id" />
    <Field jname="モバイルUID" name="mobile_uid" field="w2_User.mobile_uid" />
    <Field jname="リモートIPアドレス" name="remote_addr" field="w2_User.remote_addr" />
    <Field jname="メール配信フラグ" name="mail_flg" field="w2_User.mail_flg" />
    <Field jname="かんたん会員フラグ" name="easy_register_flg" field="w2_User.easy_register_flg" />
    <Field jname="ユーザー特記欄" name="user_memo" field="w2_User.user_memo" />
    <!-- アフィリエイトOP用 -->
    <Field jname="広告コード" name="advcode_first" field="w2_User.advcode_first" />
    <Field jname="削除フラグ" name="del_flg" field="w2_User.del_flg" />
    <Field jname="作成日" name="date_created" field="w2_User.date_created" type="datetime" />
    <Field jname="更新日" name="date_changed" field="w2_User.date_changed" type="datetime" />
    <Field jname="最終更新者" name="last_changed" field="w2_User.last_changed" />
    <Field jname="会員ランクID" name="member_rank_id" field="w2_User.member_rank_id" />
    <Field jname="最終ログイン日時" name ="date_last_loggedin" field="w2_User.date_last_loggedin" type="datetime" />
    <Field jname="ユーザー管理レベルID" name="user_management_level_id" field="w2_User.user_management_level_id" />
    <Field jname="ユーザー統合フラグ" name="integrated_flg" field="w2_User.integrated_flg" />
    <!-- グローバル対応 -->
    <Field jname="アクセス国ISOコード" name="access_country_iso_code" field="w2_User.access_country_iso_code" option="global" />
    <Field jname="表示言語コード" name="disp_language_code" field="w2_User.disp_language_code" option="global" />
    <Field jname="表示言語ロケールID" name="disp_language_locale_id" field="w2_User.disp_language_locale_id" option="global" />
    <Field jname="表示通貨コード" name="disp_currency_code" field="w2_User.disp_currency_code" option="global" />
    <Field jname="表示通貨ロケールID" name="disp_currency_locale_id" field="w2_User.disp_currency_locale_id" option="global" />
  </TargetListData>
  <!-- ターゲットリストのユーザーマスタ設定に追加される（ユーザー＋拡張項目＋ユーザー属性） -->
  <TargetListDataUserAttribute>
    <Field jname="初回購入日" name="first_order_date" field="w2_UserAttribute.first_order_date" option="user_attribute" type="datetime" />
    <Field jname="２回目購入日" name="second_order_date" field="w2_UserAttribute.second_order_date" option="user_attribute" type="datetime" />
    <Field jname="最終購入日" name="last_order_date" field="w2_UserAttribute.last_order_date" option="user_attribute" type="datetime" />
    <Field jname="在籍期間(日)" name="enrollment_days" field="w2_UserAttribute.enrollment_days" option="user_attribute" />
    <Field jname="離脱期間(日)" name="away_days" field="w2_UserAttribute.away_days" option="user_attribute" />
    <Field jname="累計購入金額（注文基準・全体）" name="order_amount_order_all" field="w2_UserAttribute.order_amount_order_all" option="user_attribute" type="price" />
    <Field jname="累計購入金額（注文基準・定期のみ）" name="order_amount_order_fp" field="w2_UserAttribute.order_amount_order_fp" option="user_attribute" type="price" />
    <Field jname="累計購入回数（注文基準・全体）" name="order_count_order_all" field="w2_UserAttribute.order_count_order_all" option="user_attribute" />
    <Field jname="累計購入回数（注文基準・定期のみ）" name="order_count_order_fp" field="w2_UserAttribute.order_count_order_fp" option="user_attribute" />
    <Field jname="累計購入金額（出荷基準・全体）" name="order_amount_ship_all" field="w2_UserAttribute.order_amount_ship_all" option="user_attribute" />
    <Field jname="累計購入金額（出荷基準・定期のみ）" name="order_amount_ship_fp" field="w2_UserAttribute.order_amount_ship_fp" option="user_attribute" type="price"/>
    <Field jname="累計購入回数（出荷基準・全体）" name="order_count_ship_all" field="w2_UserAttribute.order_count_ship_all" option="user_attribute" type="price" />
    <Field jname="累計購入回数（出荷基準・定期のみ）" name="order_count_ship_fp" field="w2_UserAttribute.order_count_ship_fp" option="user_attribute" />
    <Field jname="集計日" name="attribute_date_changed" field="w2_UserAttribute.date_changed AS attribute_date_changed" type="datetime" option="user_attribute" />
    <Field jname="CPMクラスタ属性1" name="cpm_cluster_attribute1" field="w2_UserAttribute.cpm_cluster_attribute1" option="cpm" />
    <Field jname="CPMクラスタ属性2" name="cpm_cluster_attribute2" field="w2_UserAttribute.cpm_cluster_attribute2" option="cpm" />
    <Field jname="CPMクラスタID" name="cpm_cluster_id" field="w2_UserAttribute.cpm_cluster_id" option="cpm" />
    <Field jname="以前のCPMクラスタ属性1" name="cpm_cluster_attribute1_before" field="w2_UserAttribute.cpm_cluster_attribute1_before" option="cpm" />
    <Field jname="以前のCPMクラスタ属性2" name="cpm_cluster_attribute2_before" field="w2_UserAttribute.cpm_cluster_attribute2_before" option="cpm" />
    <Field jname="以前のCPMクラスタID" name="cpm_cluster_id_before" field="w2_UserAttribute.cpm_cluster_id_before" option="cpm" />
    <Field jname="CPMクラスタ変更日" name="cpm_cluster_changed_date" field="w2_UserAttribute.cpm_cluster_changed_date" option="cpm" type="datetime" />
  </TargetListDataUserAttribute>
  <!--広告コード情報-->
  <AdvCode>
    <Field jname="広告コードNO" name="advcode_no" field="w2_AdvCode.advcode_no" />
    <Field jname="識別NO" name="dept_id" field="w2_AdvCode.dept_id" />
    <Field jname="広告コード" name="advertisement_code" field="w2_AdvCode.advertisement_code" />
    <Field jname="媒体名" name="media_name" field="w2_AdvCode.media_name" />
    <Field jname="有効フラグ" name="valid_flg" field="w2_AdvCode.valid_flg" />
    <Field jname="作成日" name="date_created" field="w2_AdvCode.date_created" type="datetime" />
    <Field jname="更新日" name="date_changed" field="w2_AdvCode.date_changed" type="datetime" />
    <Field jname="最終更新者" name="last_changed" field="w2_AdvCode.last_changed" />
    <Field jname="出稿日" name="advertisement_date" field="w2_AdvCode.advertisement_date" type="datetime" />
    <Field jname="媒体費" name="media_cost" field="w2_AdvCode.media_cost" type="price" />
    <Field jname="備考" name="memo" field="w2_AdvCode.memo" />
    <Field jname="媒体掲載期間(From)" name="publication_date_from" field="w2_AdvCode.publication_date_from" type="datetime" />
    <Field jname="媒体掲載期間(To)" name="publication_date_to" field="w2_AdvCode.publication_date_to" type="datetime" />
    <Field jname="広告媒体区分" name="advcode_media_type_id" field="w2_AdvCode.advcode_media_type_id" />
    <Field jname="会員登録時紐づけ会員ランク" name="member_rank_id_granted_at_account_registration" field="w2_AdvCode.member_rank_id_granted_at_account_registration" />
    <Field jname="会員登録時紐づけユーザー管理レベル" name="user_management_level_id_granted_at_account_registration" field="w2_AdvCode.user_management_level_id_granted_at_account_registration" />
  </AdvCode>
  <!--AdvCodeMediaType-->
  <AdvCodeMediaType>
    <Field jname="区分ID" name="advcode_media_type_id" field="w2_AdvCodeMediaType.advcode_media_type_id" />
    <Field jname="区分名" name="advcode_media_type_name" field="w2_AdvCodeMediaType.advcode_media_type_name" />
    <Field jname="表示順" name="display_order" field="w2_AdvCodeMediaType.display_order" />
    <Field jname="作成日" name="date_created" field="w2_AdvCodeMediaType.date_created" type="datetime" />
    <Field jname="更新日" name="date_changed" field="w2_AdvCodeMediaType.date_changed" type="datetime" />
    <Field jname="最終更新者" name="last_changed" field="w2_AdvCodeMediaType.last_changed" />
  </AdvCodeMediaType>
  <!--ユーザーポイント情報-->
  <UserPoint>
    <Field jname="ユーザーID" name="user_id" field="w2_User.user_id" />
    <Field jname="氏名" name="name" field="w2_User.name" />
    <Field jname="本ポイント" name="point" field="UserPoint_CTE.point" />
    <Field jname="仮ポイント" name="point_temp" field="UserPointTemp_CTE.point_temp" />
    <Field jname="有効期限" name="point_exp" field="UserPoint_CTE.point_exp" type="datetime" />
  </UserPoint>
  <!--ユーザーポイント情報(詳細)-->
  <UserPointDetail>
    <Field jname="ユーザーID" name="user_id" field="w2_User.user_id" />
    <Field jname="氏名" name="name" field="w2_User.name" />
    <Field jname="ポイント区分" name="point_kbn" field="w2_UserPoint.point_kbn" />
    <Field jname="ポイント種別" name="point_type" field="w2_UserPoint.point_type" />
    <Field jname="ポイント" name="point" field="w2_UserPoint.point" />
    <Field jname="利用可能期間開始日" name="effective_date" field="w2_UserPoint.effective_date" type="datetime" />
    <Field jname="有効期限" name="point_exp" field="w2_UserPoint.point_exp" type="datetime" />
    <Field jname="予備区分1" name="kbn1" field="w2_UserPoint.kbn1" />
  </UserPointDetail>
  <!--クーポン情報-->
  <Coupon>
    <Field jname="識別ID" name="dept_id" field="w2_Coupon.dept_id" />
    <Field jname="クーポンID" name="coupon_id" field="w2_Coupon.coupon_id" />
    <Field jname="クーポンコード" name="coupon_code" field="w2_Coupon.coupon_code" />
    <Field jname="管理用クーポン名" name="coupon_name" field="w2_Coupon.coupon_name" />
    <Field jname="表示用クーポン名" name="coupon_disp_name" field="w2_Coupon.coupon_disp_name" />
    <Field jname="モバイル用表示用クーポン名" name="coupon_disp_name_mobile" field="w2_Coupon.coupon_disp_name_mobile" />
    <Field jname="クーポン説明文" name="coupon_discription" field="w2_Coupon.coupon_discription" />
    <Field jname="モバイル用クーポン説明文" name="coupon_discription_mobile" field="w2_Coupon.coupon_discription_mobile" />
    <Field jname="クーポン種別" name="coupon_type" field="w2_Coupon.coupon_type" />
    <Field jname="クーポン利用可能回数" name="coupon_count" field="w2_Coupon.coupon_count" />
    <Field jname="クーポン発行期間(開始)" name="publish_date_bgn" field="w2_Coupon.publish_date_bgn" type="datetime" />
    <Field jname="クーポン発行期間(終了)" name="publish_date_end" field="w2_Coupon.publish_date_end" type="datetime" />
    <Field jname="クーポン商品割引額" name="discount_price" field="w2_Coupon.discount_price" type="price" />
    <Field jname="クーポン商品割引率" name="discount_rate" field="w2_Coupon.discount_rate" />
    <Field jname="クーポン有効期限(日)" name="expire_day" field="w2_Coupon.expire_day" />
    <Field jname="クーポン有効期間(開始)" name="expire_date_bgn" field="w2_Coupon.expire_date_bgn" type="datetime" />
    <Field jname="クーポン有効期間(終了)" name="expire_date_end" field="w2_Coupon.expire_date_end" type="datetime" />
    <Field jname="クーポン対象商品区分" name="product_kbn" field="w2_Coupon.product_kbn" />
    <Field jname="クーポン例外ブランドID" name="exceptional_brand_ids" field="w2_Coupon.exceptional_brand_ids" />
    <Field jname="クーポン例外商品カテゴリID" name="exceptional_product_category_ids" field="w2_Coupon.exceptional_product_category_ids" />
    <Field jname="クーポン例外商品" name="exceptional_product" field="w2_Coupon.exceptional_product" />
    <Field jname="クーポン例外商品アイコン" name="exceptional_icon" field="w2_Coupon.exceptional_icon" />
    <Field jname="クーポン利用最低購入金額" name="usable_price" field="w2_Coupon.usable_price" type="price" />
    <Field jname="クーポン併用フラグ" name="use_together_flg" field="w2_Coupon.use_together_flg" />
    <Field jname="有効フラグ" name="valid_flg" field="w2_Coupon.valid_flg" />
    <Field jname="作成日" name="date_created" field="w2_Coupon.date_created" type="datetime" />
    <Field jname="更新日" name="date_changed" field="w2_Coupon.date_changed" type="datetime" />
    <Field jname="最終更新者" name="last_changed" field="w2_Coupon.last_changed" />
    <Field jname="フロント表示フラグ" name="disp_flg" field="w2_Coupon.disp_flg" />
    <Field jname="フロント表示用クーポン説明文" name="coupon_disp_discription" field="w2_Coupon.coupon_disp_discription" />
    <Field jname="クーポン配送料無料フラグ" name="free_shipping_flg" field="w2_Coupon.free_shipping_flg" />
  </Coupon>
  <!--ユーザクーポン情報-->
  <UserCoupon>
    <Field jname="ユーザID" name="user_id" field="w2_UserCoupon.user_id" />
    <Field jname="識別ID" name="dept_id" field="w2_UserCoupon.dept_id" />
    <Field jname="クーポンID" name="coupon_id" field="w2_UserCoupon.coupon_id" />
    <Field jname="クーポンコード" name="coupon_code" field="w2_Coupon.coupon_code" />
    <Field jname="枝番" name="coupon_no" field="w2_UserCoupon.coupon_no" />
    <Field jname="注文ID" name="order_id" field="w2_UserCoupon.order_id" />
    <Field jname="利用フラグ" name="use_flg" field="w2_UserCoupon.use_flg" />
    <Field jname="利用可能回数" name="user_coupon_count" field="w2_UserCoupon.user_coupon_count" />
    <Field jname="作成日" name="date_created" field="w2_UserCoupon.date_created" type="datetime" />
    <Field jname="更新日" name="date_changed" field="w2_UserCoupon.date_changed" type="datetime" />
    <Field jname="最終更新者" name="last_changed" field="w2_UserCoupon.last_changed" />
  </UserCoupon>
  <!-- クーポン利用ユーザー情報 -->
  <CouponUseUser>
    <Field jname="クーポンコード" name="coupon_code" field="w2_Coupon.coupon_code" />
    <Field jname="クーポン利用ユーザー" name="coupon_use_user" field="w2_CouponUseUser.coupon_use_user" />
    <Field jname="注文ID" name="order_id" field="w2_CouponUseUser.order_id" />
    <Field jname="定期購入ID" name="fixed_purchase_id" field="w2_CouponUseUser.fixed_purchase_id" />
    <Field jname="作成日" name="date_created" field="w2_CouponUseUser.date_created" type="datetime" />
    <Field jname="最終更新者" name="last_changed" field="w2_CouponUseUser.last_changed" />
  </CouponUseUser>
  <!-- Extend title -->
  <ExtendTitle>
    <Field jname="拡張項目：{0}" name="" field="" />
  </ExtendTitle>

</MasterExportSetting>
